plastik/__init__.py
plastik/airport.py
plastik/axes.py
plastik/colors.py
plastik/default.mplstyle
plastik/grid.py
plastik/legends.py
plastik/lines.py
plastik/percentiles.py
plastik/ridge.py
plastik-0.11.1.dist-info/METADATA
plastik-0.11.1.dist-info/WHEEL
plastik-0.11.1.dist-info/licenses/LICENSE
plastik-0.11.1.dist-info/RECORD
