Metadata-Version: 2.4
Name: plastik
Version: 0.11.1
Summary: plastic surgery for plt
Project-URL: homepage, https://github.com/engeir/plastik
Project-URL: repository, https://github.com/engeir/plastik
Project-URL: documentation, https://plastik.readthedocs.io/en/latest/
Author-email: engeir <engeir@pm.me>
License:                     GNU GENERAL PUBLIC LICENSE
License-File: LICENSE
Classifier: Programming Language :: Python :: 3.10
Classifier: Programming Language :: Python :: 3.11
Classifier: Programming Language :: Python :: 3.12
Requires-Python: <3.13,>=3.10
Requires-Dist: attrs>=23.2.0
Requires-Dist: cmcrameri>=1.8
Requires-Dist: matplotlib>=3.7.5
Requires-Dist: numpy>=1.24.4
Requires-Dist: palettable>=3.3.3
Requires-Dist: pywaffle>=1.1.0
Requires-Dist: typing-extensions>=4.12.2
Provides-Extra: extra
Requires-Dist: fppanalysis; extra == 'extra'
Requires-Dist: scipy>=1.14.1; extra == 'extra'
